{
  "snapshot_date": "2026-06-17",
  "fetched_at": "2026-06-17T05:41:53.665410Z",
  "source": "api",
  "guild_slug": "xieruisi",
  "guild_name": "希尔锐斯",
  "guild_id": "6421160c7836d519149fa8c9",
  "guild_url": "https://www.titansdb.com/guilds/6421160c7836d519149fa8c9",
  "api_url": "https://www.titansdb.com/api/guild/6421160c7836d519149fa8c9",
  "ok": true,
  "members": [
    {
      "last_update": "2026-06-17 02:23:22",
      "id": "5e4029d4068d3a11713667de",
      "name": "天凉好个秋#33444",
      "level": 81,
      "isVip": false,
      "banned": false,
      "last_online": "2026-06-16 13:54:56",
      "guild": {
        "rank": "Guildmaster",
        "joined": "2026-03-19 10:52:35"
      },
      "stats": {
        "networth": 754019528075,
        "investments": 302880638400,
        "help": 1560,
        "bounty": 1425,
        "prestige": 16455,
        "mastered": 414,
        "masteredSF": 0,
        "ascensions": 380,
        "collection": 9011,
        "total_crafted": 83336,
        "total_sold": 215057,
        "total_quests": 10380,
        "total_chests": 2000,
        "best_hero_power": 117168
      },
      "events": {
        "current_event_score": 2757,
        "best_lcog_score": 8555,
        "best_kc_score": 4318313,
        "best_di_score": 353838
      }
    },
    {
      "last_update": "2026-06-17 00:45:40",
      "id": "6805fc5573e08ceb9c99e7f7",
      "name": "雾青丝#39731",
      "level": 96,
      "isVip": false,
      "banned": false,
      "last_online": "2026-06-15 01:02:10",
      "guild": {
        "rank": "Officer",
        "joined": "2026-05-19 02:33:40"
      },
      "stats": {
        "networth": 4156172825922,
        "investments": 642709988400,
        "help": 4753,
        "bounty": 19816,
        "prestige": 14985,
        "mastered": 427,
        "masteredSF": 0,
        "ascensions": 609,
        "collection": 12195,
        "total_crafted": 601411,
        "total_sold": 679172,
        "total_quests": 8413,
        "total_chests": 1364,
        "best_hero_power": 567050
      },
      "events": {
        "current_event_score": 3208,
        "best_lcog_score": 24040,
        "best_kc_score": 8057025,
        "best_di_score": 1027898
      }
    },
    {
      "last_update": "2026-06-14 17:01:09",
      "id": "5e626fea626bb71218241f71",
      "name": "会计师#29722",
      "level": 71,
      "isVip": false,
      "banned": false,
      "last_online": "2026-05-21 04:17:18",
      "guild": {
        "rank": "Officer",
        "joined": "2026-03-19 10:24:47"
      },
      "stats": {
        "networth": 156217601795,
        "investments": 251807374500,
        "help": 3311,
        "bounty": 1341,
        "prestige": 48905,
        "mastered": 68,
        "masteredSF": 0,
        "ascensions": 219,
        "collection": 2169,
        "total_crafted": 25019,
        "total_sold": 48849,
        "total_quests": 5679,
        "total_chests": 892,
        "best_hero_power": 410010
      },
      "events": {
        "current_event_score": 0,
        "best_lcog_score": 15751,
        "best_kc_score": 3497928,
        "best_di_score": 847630
      }
    },
    {
      "last_update": "2026-06-16 20:46:11",
      "id": "67b46d46665600d22d6a5ab1",
      "name": "清素笔调#12295",
      "level": 64,
      "isVip": false,
      "banned": false,
      "last_online": "2026-06-16 13:46:20",
      "guild": {
        "rank": "Officer",
        "joined": "2026-05-13 13:25:07"
      },
      "stats": {
        "networth": 20875450630,
        "investments": 112167374500,
        "help": 4577,
        "bounty": 2781,
        "prestige": 3075,
        "mastered": 151,
        "masteredSF": 0,
        "ascensions": 43,
        "collection": 932,
        "total_crafted": 33239,
        "total_sold": 42336,
        "total_quests": 1460,
        "total_chests": 33,
        "best_hero_power": 2232
      },
      "events": {
        "current_event_score": 0,
        "best_lcog_score": 581,
        "best_kc_score": 10894,
        "best_di_score": 56375
      }
    },
    {
      "last_update": "2026-06-16 22:27:00",
      "id": "69d0a72ea36fa02151a7136b",
      "name": "四暮暮暮#36166",
      "level": 58,
      "isVip": true,
      "banned": false,
      "last_online": "2026-06-17 03:10:05",
      "guild": {
        "rank": "Officer",
        "joined": "2026-05-19 13:12:55"
      },
      "stats": {
        "networth": 9243695839,
        "investments": 25158924500,
        "help": 1109,
        "bounty": 2061,
        "prestige": 28685,
        "mastered": 298,
        "masteredSF": 18,
        "ascensions": 94,
        "collection": 3521,
        "total_crafted": 28148,
        "total_sold": 30339,
        "total_quests": 2690,
        "total_chests": 475,
        "best_hero_power": 8213
      },
      "events": {
        "current_event_score": 943,
        "best_lcog_score": 1049,
        "best_kc_score": 360318,
        "best_di_score": 35119
      }
    },
    {
      "last_update": "2026-06-17 01:51:11",
      "id": "663ba9bf44dc9ac80776a27a",
      "name": "MagicMirror#39146",
      "level": 56,
      "isVip": false,
      "banned": false,
      "last_online": "2026-06-17 02:29:01",
      "guild": {
        "rank": "Officer",
        "joined": "2026-04-26 03:49:10"
      },
      "stats": {
        "networth": 4005779036,
        "investments": 7123913500,
        "help": 3382,
        "bounty": 1941,
        "prestige": 35265,
        "mastered": 244,
        "masteredSF": 0,
        "ascensions": 187,
        "collection": 5698,
        "total_crafted": 45385,
        "total_sold": 50914,
        "total_quests": 2915,
        "total_chests": 203,
        "best_hero_power": 18332
      },
      "events": {
        "current_event_score": 582,
        "best_lcog_score": 603,
        "best_kc_score": 351514,
        "best_di_score": 62686
      }
    },
    {
      "last_update": "2026-06-16 12:34:35",
      "id": "692d91c0bf91ac66c00eccf3",
      "name": "天才呀#40183",
      "level": 65,
      "isVip": true,
      "banned": false,
      "last_online": "2026-06-17 03:10:27",
      "guild": {
        "rank": "Officer",
        "joined": "2026-05-18 15:24:57"
      },
      "stats": {
        "networth": 22616279643,
        "investments": 5121195100,
        "help": 1697,
        "bounty": 1546,
        "prestige": 32495,
        "mastered": 252,
        "masteredSF": 5,
        "ascensions": 169,
        "collection": 4368,
        "total_crafted": 71677,
        "total_sold": 61681,
        "total_quests": 3024,
        "total_chests": 634,
        "best_hero_power": 37820
      },
      "events": {
        "current_event_score": 1815,
        "best_lcog_score": 2065,
        "best_kc_score": 230262,
        "best_di_score": 86121
      }
    },
    {
      "last_update": "2026-06-16 21:45:32",
      "id": "69b94d6f0e001ce3f8df7efa",
      "name": "Klein#10782",
      "level": 56,
      "isVip": true,
      "banned": false,
      "last_online": "2026-06-17 01:57:38",
      "guild": {
        "rank": "Officer",
        "joined": "2026-03-21 01:07:52"
      },
      "stats": {
        "networth": 5720440150,
        "investments": 531339700,
        "help": 2003,
        "bounty": 1543,
        "prestige": 7585,
        "mastered": 84,
        "masteredSF": 6,
        "ascensions": 250,
        "collection": 1547,
        "total_crafted": 14111,
        "total_sold": 22294,
        "total_quests": 2040,
        "total_chests": 517,
        "best_hero_power": 13826
      },
      "events": {
        "current_event_score": 1209,
        "best_lcog_score": 1923,
        "best_kc_score": 183914,
        "best_di_score": 44166
      }
    },
    {
      "last_update": "2026-06-16 21:40:06",
      "id": "5f700930031a301329a11eee",
      "name": "yiyi11494#13953",
      "level": 76,
      "isVip": false,
      "banned": false,
      "last_online": "2026-06-17 04:19:25",
      "guild": {
        "rank": "Member",
        "joined": "2026-04-21 01:05:50"
      },
      "stats": {
        "networth": 223484553699,
        "investments": 30585038400,
        "help": 4753,
        "bounty": 23748,
        "prestige": 57190,
        "mastered": 563,
        "masteredSF": 6,
        "ascensions": 323,
        "collection": 20295,
        "total_crafted": 940702,
        "total_sold": 684578,
        "total_quests": 27806,
        "total_chests": 3739,
        "best_hero_power": 20009
      },
      "events": {
        "current_event_score": 1022,
        "best_lcog_score": 2698,
        "best_kc_score": 2807214,
        "best_di_score": 239420
      }
    },
    {
      "last_update": "2026-06-16 13:28:11",
      "id": "69ba35bc0e001ce3f8df8868",
      "name": "时夜雨#67267",
      "level": 52,
      "isVip": false,
      "banned": false,
      "last_online": "2026-06-17 05:13:22",
      "guild": {
        "rank": "Member",
        "joined": "2026-05-19 03:29:41"
      },
      "stats": {
        "networth": 684760485,
        "investments": 18905074500,
        "help": 1443,
        "bounty": 1060,
        "prestige": 8235,
        "mastered": 72,
        "masteredSF": 2,
        "ascensions": 69,
        "collection": 893,
        "total_crafted": 13955,
        "total_sold": 17486,
        "total_quests": 1469,
        "total_chests": 290,
        "best_hero_power": 6861
      },
      "events": {
        "current_event_score": 783,
        "best_lcog_score": 783,
        "best_kc_score": 95298,
        "best_di_score": 45087
      }
    },
    {
      "last_update": "2026-06-17 03:20:34",
      "id": "5eb693952d9e80123ae02639",
      "name": "Shan*_*FOX#42418",
      "level": 49,
      "isVip": true,
      "banned": false,
      "last_online": "2026-06-17 03:13:28",
      "guild": {
        "rank": "Member",
        "joined": "2026-03-20 12:00:53"
      },
      "stats": {
        "networth": 459071929,
        "investments": 15826111000,
        "help": 1107,
        "bounty": 1673,
        "prestige": 14540,
        "mastered": 72,
        "masteredSF": 1,
        "ascensions": 228,
        "collection": 1269,
        "total_crafted": 12903,
        "total_sold": 13263,
        "total_quests": 1171,
        "total_chests": 233,
        "best_hero_power": 13649
      },
      "events": {
        "current_event_score": 1621,
        "best_lcog_score": 1621,
        "best_kc_score": 127546,
        "best_di_score": 68545
      }
    },
    {
      "last_update": "2026-06-16 21:11:23",
      "id": "6306a4f0b67b1f12f03774c7",
      "name": "5277#57894",
      "level": 62,
      "isVip": false,
      "banned": false,
      "last_online": "2026-06-16 15:29:39",
      "guild": {
        "rank": "Member",
        "joined": "2026-05-16 04:54:55"
      },
      "stats": {
        "networth": 6724199734,
        "investments": 14488599500,
        "help": 852,
        "bounty": 33,
        "prestige": 43875,
        "mastered": 170,
        "masteredSF": 1,
        "ascensions": 218,
        "collection": 1274,
        "total_crafted": 26470,
        "total_sold": 36771,
        "total_quests": 3815,
        "total_chests": 546,
        "best_hero_power": 22960
      },
      "events": {
        "current_event_score": 0,
        "best_lcog_score": 1271,
        "best_kc_score": 330024,
        "best_di_score": 41833
      }
    },
    {
      "last_update": "2026-06-16 19:41:41",
      "id": "620b4995245f6e12f3cd1b53",
      "name": "Penny L#39430",
      "level": 58,
      "isVip": false,
      "banned": false,
      "last_online": "2026-06-17 02:35:10",
      "guild": {
        "rank": "Member",
        "joined": "2026-05-18 09:01:52"
      },
      "stats": {
        "networth": 2134854579,
        "investments": 10390919000,
        "help": 2759,
        "bounty": 2047,
        "prestige": 47430,
        "mastered": 213,
        "masteredSF": 3,
        "ascensions": 351,
        "collection": 3763,
        "total_crafted": 67585,
        "total_sold": 66973,
        "total_quests": 6040,
        "total_chests": 414,
        "best_hero_power": 9019
      },
      "events": {
        "current_event_score": 590,
        "best_lcog_score": 943,
        "best_kc_score": 91484,
        "best_di_score": 52356
      }
    },
    {
      "last_update": "2026-06-16 15:12:26",
      "id": "5e6ef23469f6ee121b57912e",
      "name": "Clodday#53519",
      "level": 62,
      "isVip": false,
      "banned": false,
      "last_online": "2026-06-17 05:08:03",
      "guild": {
        "rank": "Member",
        "joined": "2026-04-24 00:21:36"
      },
      "stats": {
        "networth": 13054627335,
        "investments": 4836266200,
        "help": 6117,
        "bounty": 932,
        "prestige": 87555,
        "mastered": 241,
        "masteredSF": 0,
        "ascensions": 345,
        "collection": 3442,
        "total_crafted": 47313,
        "total_sold": 43793,
        "total_quests": 8349,
        "total_chests": 807,
        "best_hero_power": 23872
      },
      "events": {
        "current_event_score": 1248,
        "best_lcog_score": 2797,
        "best_kc_score": 500003,
        "best_di_score": 138460
      }
    },
    {
      "last_update": "2026-06-16 09:39:26",
      "id": "62a069ea85c2db12dcaad220",
      "name": "天打雷劈#91827",
      "level": 56,
      "isVip": false,
      "banned": false,
      "last_online": "2026-06-15 13:56:15",
      "guild": {
        "rank": "Member",
        "joined": "2026-05-26 12:58:28"
      },
      "stats": {
        "networth": 6310927399,
        "investments": 4110574500,
        "help": 638,
        "bounty": 968,
        "prestige": 11350,
        "mastered": 153,
        "masteredSF": 3,
        "ascensions": 102,
        "collection": 1496,
        "total_crafted": 19739,
        "total_sold": 23987,
        "total_quests": 1286,
        "total_chests": 242,
        "best_hero_power": 8607
      },
      "events": {
        "current_event_score": 140,
        "best_lcog_score": 1033,
        "best_kc_score": 107157,
        "best_di_score": 41072
      }
    },
    {
      "last_update": "2026-06-16 13:58:14",
      "id": "69b7a790fa63a8a3ae71a7d2",
      "name": "渔洲渡#24911",
      "level": 61,
      "isVip": false,
      "banned": false,
      "last_online": "2026-06-15 16:58:11",
      "guild": {
        "rank": "Member",
        "joined": "2026-05-19 02:32:00"
      },
      "stats": {
        "networth": 11157498474,
        "investments": 3335815500,
        "help": 1604,
        "bounty": 1647,
        "prestige": 27070,
        "mastered": 263,
        "masteredSF": 1,
        "ascensions": 128,
        "collection": 2748,
        "total_crafted": 22655,
        "total_sold": 32736,
        "total_quests": 1993,
        "total_chests": 557,
        "best_hero_power": 13856
      },
      "events": {
        "current_event_score": 838,
        "best_lcog_score": 2316,
        "best_kc_score": 341222,
        "best_di_score": 78612
      }
    },
    {
      "last_update": "2026-06-16 13:28:17",
      "id": "659c3e2ee54e0360bb858e59",
      "name": "潘小闲#78923",
      "level": 65,
      "isVip": true,
      "banned": false,
      "last_online": "2026-06-16 22:01:40",
      "guild": {
        "rank": "Member",
        "joined": "2026-05-13 13:43:34"
      },
      "stats": {
        "networth": 25944682517,
        "investments": 2834962500,
        "help": 877,
        "bounty": 2240,
        "prestige": 10640,
        "mastered": 118,
        "masteredSF": 3,
        "ascensions": 45,
        "collection": 1292,
        "total_crafted": 42872,
        "total_sold": 69314,
        "total_quests": 3087,
        "total_chests": 349,
        "best_hero_power": 10743
      },
      "events": {
        "current_event_score": 737,
        "best_lcog_score": 737,
        "best_kc_score": 146645,
        "best_di_score": 25117
      }
    },
    {
      "last_update": "2026-06-17 03:30:00",
      "id": "5e46e62406ba35116a40b71e",
      "name": "赖赖小姐#66674",
      "level": 63,
      "isVip": false,
      "banned": false,
      "last_online": "2026-06-17 01:41:23",
      "guild": {
        "rank": "Member",
        "joined": "2026-05-04 17:09:21"
      },
      "stats": {
        "networth": 8774884873,
        "investments": 2762974500,
        "help": 4913,
        "bounty": 2452,
        "prestige": 48595,
        "mastered": 301,
        "masteredSF": 0,
        "ascensions": 359,
        "collection": 4212,
        "total_crafted": 55479,
        "total_sold": 73817,
        "total_quests": 10249,
        "total_chests": 1918,
        "best_hero_power": 24089
      },
      "events": {
        "current_event_score": 1232,
        "best_lcog_score": 4833,
        "best_kc_score": 281401,
        "best_di_score": 92764
      }
    },
    {
      "last_update": "2026-06-16 21:16:45",
      "id": "629324d34a110612f39273ac",
      "name": "关耀#91347",
      "level": 60,
      "isVip": false,
      "banned": false,
      "last_online": "2026-06-17 01:36:07",
      "guild": {
        "rank": "Member",
        "joined": "2026-06-14 15:52:20"
      },
      "stats": {
        "networth": 5075579241,
        "investments": 1470659200,
        "help": 2595,
        "bounty": 1511,
        "prestige": 25855,
        "mastered": 239,
        "masteredSF": 0,
        "ascensions": 37,
        "collection": 2948,
        "total_crafted": 39620,
        "total_sold": 44637,
        "total_quests": 5523,
        "total_chests": 747,
        "best_hero_power": 59871
      },
      "events": {
        "current_event_score": 1139,
        "best_lcog_score": 2011,
        "best_kc_score": 546251,
        "best_di_score": 100519
      }
    },
    {
      "last_update": "2026-06-16 21:16:45",
      "id": "629324d34a110612f39273ac",
      "name": "关耀#91347",
      "level": 60,
      "isVip": false,
      "banned": false,
      "last_online": "2026-06-17 01:36:07",
      "guild": {
        "rank": "Member",
        "joined": "2026-06-14 15:52:20"
      },
      "stats": {
        "networth": 5075579241,
        "investments": 1470659200,
        "help": 2595,
        "bounty": 1511,
        "prestige": 25855,
        "mastered": 239,
        "masteredSF": 0,
        "ascensions": 37,
        "collection": 2948,
        "total_crafted": 39620,
        "total_sold": 44637,
        "total_quests": 5523,
        "total_chests": 747,
        "best_hero_power": 59871
      },
      "events": {
        "current_event_score": 23,
        "best_lcog_score": 2011,
        "best_kc_score": 546251,
        "best_di_score": 100519
      }
    },
    {
      "last_update": "2026-06-16 14:24:49",
      "id": "637c96695c732e60e22178b9",
      "name": "MidgartFish#40032",
      "level": 38,
      "isVip": false,
      "banned": false,
      "last_online": "2026-06-16 11:26:25",
      "guild": {
        "rank": "Member",
        "joined": "2026-05-18 13:45:04"
      },
      "stats": {
        "networth": 74962059,
        "investments": 19742700,
        "help": 349,
        "bounty": 19,
        "prestige": 12735,
        "mastered": 15,
        "masteredSF": 0,
        "ascensions": 1,
        "collection": 254,
        "total_crafted": 3933,
        "total_sold": 4804,
        "total_quests": 461,
        "total_chests": 60,
        "best_hero_power": 3925
      },
      "events": {
        "current_event_score": 625,
        "best_lcog_score": 625,
        "best_kc_score": 6613,
        "best_di_score": 15527
      }
    }
  ],
  "raw": {
    "ok": true,
    "credits_remaining": 21,
    "guild": {
      "last_update": "2026-06-17 05:17:14",
      "id": "6421160c7836d519149fa8c9",
      "name": "希尔锐斯",
      "level": 158,
      "population": 20,
      "capacity": 20,
      "networth": 1457067486100,
      "rank": 2081,
      "members": [
        {
          "last_update": "2026-06-17 02:23:22",
          "id": "5e4029d4068d3a11713667de",
          "name": "天凉好个秋#33444",
          "level": 81,
          "isVip": false,
          "banned": false,
          "last_online": "2026-06-16 13:54:56",
          "guild": {
            "rank": "Guildmaster",
            "joined": "2026-03-19 10:52:35"
          },
          "stats": {
            "networth": 754019528075,
            "investments": 302880638400,
            "help": 1560,
            "bounty": 1425,
            "prestige": 16455,
            "mastered": 414,
            "masteredSF": 0,
            "ascensions": 380,
            "collection": 9011,
            "total_crafted": 83336,
            "total_sold": 215057,
            "total_quests": 10380,
            "total_chests": 2000,
            "best_hero_power": 117168
          },
          "events": {
            "current_event_score": 2757,
            "best_lcog_score": 8555,
            "best_kc_score": 4318313,
            "best_di_score": 353838
          }
        },
        {
          "last_update": "2026-06-17 00:45:40",
          "id": "6805fc5573e08ceb9c99e7f7",
          "name": "雾青丝#39731",
          "level": 96,
          "isVip": false,
          "banned": false,
          "last_online": "2026-06-15 01:02:10",
          "guild": {
            "rank": "Officer",
            "joined": "2026-05-19 02:33:40"
          },
          "stats": {
            "networth": 4156172825922,
            "investments": 642709988400,
            "help": 4753,
            "bounty": 19816,
            "prestige": 14985,
            "mastered": 427,
            "masteredSF": 0,
            "ascensions": 609,
            "collection": 12195,
            "total_crafted": 601411,
            "total_sold": 679172,
            "total_quests": 8413,
            "total_chests": 1364,
            "best_hero_power": 567050
          },
          "events": {
            "current_event_score": 3208,
            "best_lcog_score": 24040,
            "best_kc_score": 8057025,
            "best_di_score": 1027898
          }
        },
        {
          "last_update": "2026-06-14 17:01:09",
          "id": "5e626fea626bb71218241f71",
          "name": "会计师#29722",
          "level": 71,
          "isVip": false,
          "banned": false,
          "last_online": "2026-05-21 04:17:18",
          "guild": {
            "rank": "Officer",
            "joined": "2026-03-19 10:24:47"
          },
          "stats": {
            "networth": 156217601795,
            "investments": 251807374500,
            "help": 3311,
            "bounty": 1341,
            "prestige": 48905,
            "mastered": 68,
            "masteredSF": 0,
            "ascensions": 219,
            "collection": 2169,
            "total_crafted": 25019,
            "total_sold": 48849,
            "total_quests": 5679,
            "total_chests": 892,
            "best_hero_power": 410010
          },
          "events": {
            "current_event_score": 0,
            "best_lcog_score": 15751,
            "best_kc_score": 3497928,
            "best_di_score": 847630
          }
        },
        {
          "last_update": "2026-06-16 20:46:11",
          "id": "67b46d46665600d22d6a5ab1",
          "name": "清素笔调#12295",
          "level": 64,
          "isVip": false,
          "banned": false,
          "last_online": "2026-06-16 13:46:20",
          "guild": {
            "rank": "Officer",
            "joined": "2026-05-13 13:25:07"
          },
          "stats": {
            "networth": 20875450630,
            "investments": 112167374500,
            "help": 4577,
            "bounty": 2781,
            "prestige": 3075,
            "mastered": 151,
            "masteredSF": 0,
            "ascensions": 43,
            "collection": 932,
            "total_crafted": 33239,
            "total_sold": 42336,
            "total_quests": 1460,
            "total_chests": 33,
            "best_hero_power": 2232
          },
          "events": {
            "current_event_score": 0,
            "best_lcog_score": 581,
            "best_kc_score": 10894,
            "best_di_score": 56375
          }
        },
        {
          "last_update": "2026-06-16 22:27:00",
          "id": "69d0a72ea36fa02151a7136b",
          "name": "四暮暮暮#36166",
          "level": 58,
          "isVip": true,
          "banned": false,
          "last_online": "2026-06-17 03:10:05",
          "guild": {
            "rank": "Officer",
            "joined": "2026-05-19 13:12:55"
          },
          "stats": {
            "networth": 9243695839,
            "investments": 25158924500,
            "help": 1109,
            "bounty": 2061,
            "prestige": 28685,
            "mastered": 298,
            "masteredSF": 18,
            "ascensions": 94,
            "collection": 3521,
            "total_crafted": 28148,
            "total_sold": 30339,
            "total_quests": 2690,
            "total_chests": 475,
            "best_hero_power": 8213
          },
          "events": {
            "current_event_score": 943,
            "best_lcog_score": 1049,
            "best_kc_score": 360318,
            "best_di_score": 35119
          }
        },
        {
          "last_update": "2026-06-17 01:51:11",
          "id": "663ba9bf44dc9ac80776a27a",
          "name": "MagicMirror#39146",
          "level": 56,
          "isVip": false,
          "banned": false,
          "last_online": "2026-06-17 02:29:01",
          "guild": {
            "rank": "Officer",
            "joined": "2026-04-26 03:49:10"
          },
          "stats": {
            "networth": 4005779036,
            "investments": 7123913500,
            "help": 3382,
            "bounty": 1941,
            "prestige": 35265,
            "mastered": 244,
            "masteredSF": 0,
            "ascensions": 187,
            "collection": 5698,
            "total_crafted": 45385,
            "total_sold": 50914,
            "total_quests": 2915,
            "total_chests": 203,
            "best_hero_power": 18332
          },
          "events": {
            "current_event_score": 582,
            "best_lcog_score": 603,
            "best_kc_score": 351514,
            "best_di_score": 62686
          }
        },
        {
          "last_update": "2026-06-16 12:34:35",
          "id": "692d91c0bf91ac66c00eccf3",
          "name": "天才呀#40183",
          "level": 65,
          "isVip": true,
          "banned": false,
          "last_online": "2026-06-17 03:10:27",
          "guild": {
            "rank": "Officer",
            "joined": "2026-05-18 15:24:57"
          },
          "stats": {
            "networth": 22616279643,
            "investments": 5121195100,
            "help": 1697,
            "bounty": 1546,
            "prestige": 32495,
            "mastered": 252,
            "masteredSF": 5,
            "ascensions": 169,
            "collection": 4368,
            "total_crafted": 71677,
            "total_sold": 61681,
            "total_quests": 3024,
            "total_chests": 634,
            "best_hero_power": 37820
          },
          "events": {
            "current_event_score": 1815,
            "best_lcog_score": 2065,
            "best_kc_score": 230262,
            "best_di_score": 86121
          }
        },
        {
          "last_update": "2026-06-16 21:45:32",
          "id": "69b94d6f0e001ce3f8df7efa",
          "name": "Klein#10782",
          "level": 56,
          "isVip": true,
          "banned": false,
          "last_online": "2026-06-17 01:57:38",
          "guild": {
            "rank": "Officer",
            "joined": "2026-03-21 01:07:52"
          },
          "stats": {
            "networth": 5720440150,
            "investments": 531339700,
            "help": 2003,
            "bounty": 1543,
            "prestige": 7585,
            "mastered": 84,
            "masteredSF": 6,
            "ascensions": 250,
            "collection": 1547,
            "total_crafted": 14111,
            "total_sold": 22294,
            "total_quests": 2040,
            "total_chests": 517,
            "best_hero_power": 13826
          },
          "events": {
            "current_event_score": 1209,
            "best_lcog_score": 1923,
            "best_kc_score": 183914,
            "best_di_score": 44166
          }
        },
        {
          "last_update": "2026-06-16 21:40:06",
          "id": "5f700930031a301329a11eee",
          "name": "yiyi11494#13953",
          "level": 76,
          "isVip": false,
          "banned": false,
          "last_online": "2026-06-17 04:19:25",
          "guild": {
            "rank": "Member",
            "joined": "2026-04-21 01:05:50"
          },
          "stats": {
            "networth": 223484553699,
            "investments": 30585038400,
            "help": 4753,
            "bounty": 23748,
            "prestige": 57190,
            "mastered": 563,
            "masteredSF": 6,
            "ascensions": 323,
            "collection": 20295,
            "total_crafted": 940702,
            "total_sold": 684578,
            "total_quests": 27806,
            "total_chests": 3739,
            "best_hero_power": 20009
          },
          "events": {
            "current_event_score": 1022,
            "best_lcog_score": 2698,
            "best_kc_score": 2807214,
            "best_di_score": 239420
          }
        },
        {
          "last_update": "2026-06-16 13:28:11",
          "id": "69ba35bc0e001ce3f8df8868",
          "name": "时夜雨#67267",
          "level": 52,
          "isVip": false,
          "banned": false,
          "last_online": "2026-06-17 05:13:22",
          "guild": {
            "rank": "Member",
            "joined": "2026-05-19 03:29:41"
          },
          "stats": {
            "networth": 684760485,
            "investments": 18905074500,
            "help": 1443,
            "bounty": 1060,
            "prestige": 8235,
            "mastered": 72,
            "masteredSF": 2,
            "ascensions": 69,
            "collection": 893,
            "total_crafted": 13955,
            "total_sold": 17486,
            "total_quests": 1469,
            "total_chests": 290,
            "best_hero_power": 6861
          },
          "events": {
            "current_event_score": 783,
            "best_lcog_score": 783,
            "best_kc_score": 95298,
            "best_di_score": 45087
          }
        },
        {
          "last_update": "2026-06-17 03:20:34",
          "id": "5eb693952d9e80123ae02639",
          "name": "Shan*_*FOX#42418",
          "level": 49,
          "isVip": true,
          "banned": false,
          "last_online": "2026-06-17 03:13:28",
          "guild": {
            "rank": "Member",
            "joined": "2026-03-20 12:00:53"
          },
          "stats": {
            "networth": 459071929,
            "investments": 15826111000,
            "help": 1107,
            "bounty": 1673,
            "prestige": 14540,
            "mastered": 72,
            "masteredSF": 1,
            "ascensions": 228,
            "collection": 1269,
            "total_crafted": 12903,
            "total_sold": 13263,
            "total_quests": 1171,
            "total_chests": 233,
            "best_hero_power": 13649
          },
          "events": {
            "current_event_score": 1621,
            "best_lcog_score": 1621,
            "best_kc_score": 127546,
            "best_di_score": 68545
          }
        },
        {
          "last_update": "2026-06-16 21:11:23",
          "id": "6306a4f0b67b1f12f03774c7",
          "name": "5277#57894",
          "level": 62,
          "isVip": false,
          "banned": false,
          "last_online": "2026-06-16 15:29:39",
          "guild": {
            "rank": "Member",
            "joined": "2026-05-16 04:54:55"
          },
          "stats": {
            "networth": 6724199734,
            "investments": 14488599500,
            "help": 852,
            "bounty": 33,
            "prestige": 43875,
            "mastered": 170,
            "masteredSF": 1,
            "ascensions": 218,
            "collection": 1274,
            "total_crafted": 26470,
            "total_sold": 36771,
            "total_quests": 3815,
            "total_chests": 546,
            "best_hero_power": 22960
          },
          "events": {
            "current_event_score": 0,
            "best_lcog_score": 1271,
            "best_kc_score": 330024,
            "best_di_score": 41833
          }
        },
        {
          "last_update": "2026-06-16 19:41:41",
          "id": "620b4995245f6e12f3cd1b53",
          "name": "Penny L#39430",
          "level": 58,
          "isVip": false,
          "banned": false,
          "last_online": "2026-06-17 02:35:10",
          "guild": {
            "rank": "Member",
            "joined": "2026-05-18 09:01:52"
          },
          "stats": {
            "networth": 2134854579,
            "investments": 10390919000,
            "help": 2759,
            "bounty": 2047,
            "prestige": 47430,
            "mastered": 213,
            "masteredSF": 3,
            "ascensions": 351,
            "collection": 3763,
            "total_crafted": 67585,
            "total_sold": 66973,
            "total_quests": 6040,
            "total_chests": 414,
            "best_hero_power": 9019
          },
          "events": {
            "current_event_score": 590,
            "best_lcog_score": 943,
            "best_kc_score": 91484,
            "best_di_score": 52356
          }
        },
        {
          "last_update": "2026-06-16 15:12:26",
          "id": "5e6ef23469f6ee121b57912e",
          "name": "Clodday#53519",
          "level": 62,
          "isVip": false,
          "banned": false,
          "last_online": "2026-06-17 05:08:03",
          "guild": {
            "rank": "Member",
            "joined": "2026-04-24 00:21:36"
          },
          "stats": {
            "networth": 13054627335,
            "investments": 4836266200,
            "help": 6117,
            "bounty": 932,
            "prestige": 87555,
            "mastered": 241,
            "masteredSF": 0,
            "ascensions": 345,
            "collection": 3442,
            "total_crafted": 47313,
            "total_sold": 43793,
            "total_quests": 8349,
            "total_chests": 807,
            "best_hero_power": 23872
          },
          "events": {
            "current_event_score": 1248,
            "best_lcog_score": 2797,
            "best_kc_score": 500003,
            "best_di_score": 138460
          }
        },
        {
          "last_update": "2026-06-16 09:39:26",
          "id": "62a069ea85c2db12dcaad220",
          "name": "天打雷劈#91827",
          "level": 56,
          "isVip": false,
          "banned": false,
          "last_online": "2026-06-15 13:56:15",
          "guild": {
            "rank": "Member",
            "joined": "2026-05-26 12:58:28"
          },
          "stats": {
            "networth": 6310927399,
            "investments": 4110574500,
            "help": 638,
            "bounty": 968,
            "prestige": 11350,
            "mastered": 153,
            "masteredSF": 3,
            "ascensions": 102,
            "collection": 1496,
            "total_crafted": 19739,
            "total_sold": 23987,
            "total_quests": 1286,
            "total_chests": 242,
            "best_hero_power": 8607
          },
          "events": {
            "current_event_score": 140,
            "best_lcog_score": 1033,
            "best_kc_score": 107157,
            "best_di_score": 41072
          }
        },
        {
          "last_update": "2026-06-16 13:58:14",
          "id": "69b7a790fa63a8a3ae71a7d2",
          "name": "渔洲渡#24911",
          "level": 61,
          "isVip": false,
          "banned": false,
          "last_online": "2026-06-15 16:58:11",
          "guild": {
            "rank": "Member",
            "joined": "2026-05-19 02:32:00"
          },
          "stats": {
            "networth": 11157498474,
            "investments": 3335815500,
            "help": 1604,
            "bounty": 1647,
            "prestige": 27070,
            "mastered": 263,
            "masteredSF": 1,
            "ascensions": 128,
            "collection": 2748,
            "total_crafted": 22655,
            "total_sold": 32736,
            "total_quests": 1993,
            "total_chests": 557,
            "best_hero_power": 13856
          },
          "events": {
            "current_event_score": 838,
            "best_lcog_score": 2316,
            "best_kc_score": 341222,
            "best_di_score": 78612
          }
        },
        {
          "last_update": "2026-06-16 13:28:17",
          "id": "659c3e2ee54e0360bb858e59",
          "name": "潘小闲#78923",
          "level": 65,
          "isVip": true,
          "banned": false,
          "last_online": "2026-06-16 22:01:40",
          "guild": {
            "rank": "Member",
            "joined": "2026-05-13 13:43:34"
          },
          "stats": {
            "networth": 25944682517,
            "investments": 2834962500,
            "help": 877,
            "bounty": 2240,
            "prestige": 10640,
            "mastered": 118,
            "masteredSF": 3,
            "ascensions": 45,
            "collection": 1292,
            "total_crafted": 42872,
            "total_sold": 69314,
            "total_quests": 3087,
            "total_chests": 349,
            "best_hero_power": 10743
          },
          "events": {
            "current_event_score": 737,
            "best_lcog_score": 737,
            "best_kc_score": 146645,
            "best_di_score": 25117
          }
        },
        {
          "last_update": "2026-06-17 03:30:00",
          "id": "5e46e62406ba35116a40b71e",
          "name": "赖赖小姐#66674",
          "level": 63,
          "isVip": false,
          "banned": false,
          "last_online": "2026-06-17 01:41:23",
          "guild": {
            "rank": "Member",
            "joined": "2026-05-04 17:09:21"
          },
          "stats": {
            "networth": 8774884873,
            "investments": 2762974500,
            "help": 4913,
            "bounty": 2452,
            "prestige": 48595,
            "mastered": 301,
            "masteredSF": 0,
            "ascensions": 359,
            "collection": 4212,
            "total_crafted": 55479,
            "total_sold": 73817,
            "total_quests": 10249,
            "total_chests": 1918,
            "best_hero_power": 24089
          },
          "events": {
            "current_event_score": 1232,
            "best_lcog_score": 4833,
            "best_kc_score": 281401,
            "best_di_score": 92764
          }
        },
        {
          "last_update": "2026-06-16 21:16:45",
          "id": "629324d34a110612f39273ac",
          "name": "关耀#91347",
          "level": 60,
          "isVip": false,
          "banned": false,
          "last_online": "2026-06-17 01:36:07",
          "guild": {
            "rank": "Member",
            "joined": "2026-06-14 15:52:20"
          },
          "stats": {
            "networth": 5075579241,
            "investments": 1470659200,
            "help": 2595,
            "bounty": 1511,
            "prestige": 25855,
            "mastered": 239,
            "masteredSF": 0,
            "ascensions": 37,
            "collection": 2948,
            "total_crafted": 39620,
            "total_sold": 44637,
            "total_quests": 5523,
            "total_chests": 747,
            "best_hero_power": 59871
          },
          "events": {
            "current_event_score": 1139,
            "best_lcog_score": 2011,
            "best_kc_score": 546251,
            "best_di_score": 100519
          }
        },
        {
          "last_update": "2026-06-16 21:16:45",
          "id": "629324d34a110612f39273ac",
          "name": "关耀#91347",
          "level": 60,
          "isVip": false,
          "banned": false,
          "last_online": "2026-06-17 01:36:07",
          "guild": {
            "rank": "Member",
            "joined": "2026-06-14 15:52:20"
          },
          "stats": {
            "networth": 5075579241,
            "investments": 1470659200,
            "help": 2595,
            "bounty": 1511,
            "prestige": 25855,
            "mastered": 239,
            "masteredSF": 0,
            "ascensions": 37,
            "collection": 2948,
            "total_crafted": 39620,
            "total_sold": 44637,
            "total_quests": 5523,
            "total_chests": 747,
            "best_hero_power": 59871
          },
          "events": {
            "current_event_score": 23,
            "best_lcog_score": 2011,
            "best_kc_score": 546251,
            "best_di_score": 100519
          }
        },
        {
          "last_update": "2026-06-16 14:24:49",
          "id": "637c96695c732e60e22178b9",
          "name": "MidgartFish#40032",
          "level": 38,
          "isVip": false,
          "banned": false,
          "last_online": "2026-06-16 11:26:25",
          "guild": {
            "rank": "Member",
            "joined": "2026-05-18 13:45:04"
          },
          "stats": {
            "networth": 74962059,
            "investments": 19742700,
            "help": 349,
            "bounty": 19,
            "prestige": 12735,
            "mastered": 15,
            "masteredSF": 0,
            "ascensions": 1,
            "collection": 254,
            "total_crafted": 3933,
            "total_sold": 4804,
            "total_quests": 461,
            "total_chests": 60,
            "best_hero_power": 3925
          },
          "events": {
            "current_event_score": 625,
            "best_lcog_score": 625,
            "best_kc_score": 6613,
            "best_di_score": 15527
          }
        }
      ]
    }
  }
}
